LICENSE
MANIFEST.in
README.rst
dweepy.py
setup.py
dweepy.egg-info/PKG-INFO
dweepy.egg-info/SOURCES.txt
dweepy.egg-info/dependency_links.txt
dweepy.egg-info/not-zip-safe
dweepy.egg-info/requires.txt
dweepy.egg-info/top_level.txt