Metadata-Version: 1.1
Name: dweepy
Version: 0.0.1
Summary: Dweepy is a Python client for dweet.io
Home-page: https://github.com/paddycarey/dweepy
Author: Patrick Carey
Author-email: paddy@wackwack.co.uk
License: MIT
Keywords: dweepy dweet dweet.io
Platform: UNKNOWN
Classifier: Development Status :: 3 - Alpha
Classifier: Intended Audience :: Developers
Classifier: License :: OSI Approved :: MIT License
Classifier: Natural Language :: English
Classifier: Programming Language :: Python :: 2
Classifier: Programming Language :: Python :: 2.6
Classifier: Programming Language :: Python :: 2.7
